pkgversioner/__init__.py
pkgversioner/check_dependencies.py
pkgversioner/check_imports.py
pkgversioner/versions.py
pkgversioner-0.1.4.dist-info/METADATA
pkgversioner-0.1.4.dist-info/WHEEL
pkgversioner-0.1.4.dist-info/RECORD
