Metadata-Version: 2.3
Name: pkgversioner
Version: 0.1.4
Summary: Package versioning tools for Python projects
Author: Danny Stewart
Author-email: danny@stewart.cc
Requires-Python: >=3.12
Classifier: Programming Language :: Python :: 3
Classifier: Programming Language :: Python :: 3.12
Classifier: Programming Language :: Python :: 3.13
Requires-Dist: arguer (>=0.1.0,<0.2.0)
Requires-Dist: packaging (>=24.2,<25.0)
Requires-Dist: requests (>=2.32.3,<3.0.0)
Requires-Dist: textparse (>=0.1.0)
